t_rex_typer/__init__.py
t_rex_typer/__main__.py
t_rex_typer/main_window.py
t_rex_typer/settings.py
t_rex_typer/steno_board.py
t_rex_typer/tab_safe_line_edit.py
t_rex_typer/text_label.py
t_rex_typer/translation_dict.py
t_rex_typer/resources/keyboard_48.png
t_rex_typer/resources/screenshot.png
t_rex_typer/resources/trex_48.png
t_rex_typer/resources/trex_96.png
t_rex_typer/resources/trex_w_board_48.png
t_rex_typer/resources/trex_w_board_96.png
t_rex_typer-0.1.6.dist-info/METADATA
t_rex_typer-0.1.6.dist-info/WHEEL
t_rex_typer-0.1.6.dist-info/entry_points.txt
t_rex_typer-0.1.6.dist-info/top_level.txt
t_rex_typer-0.1.6.dist-info/RECORD
