Metadata-Version: 2.1
Name: t-rex-typer
Version: 0.1.6
Summary: Steno practice
Home-page: https://codeberg.org/excalamus/t_rex_typer
Author: Matt Trzcinski
Author-email: matt@excalamus.com
Project-URL: Bug Reports, https://codeberg.org/excalamus/t_rex_typer/issues
Project-URL: Funding, https://donate.pypi.org
Project-URL: Source, https://codeberg.org/excalamus/t_rex_typer/
Keywords: steno,stenography
Classifier: Development Status :: 3 - Alpha
Classifier: Intended Audience :: Education
Classifier: Intended Audience :: End Users/Desktop
Classifier: Operating System :: POSIX :: Linux
Classifier: License :: OSI Approved :: GNU General Public License v3 (GPLv3)
Classifier: Programming Language :: Python :: 3
Classifier: Programming Language :: Python :: 3.9
Classifier: Programming Language :: Python :: 3 :: Only
Requires-Python: >=3.6
Requires-Dist: PySide2 (>=5.15.2)
Requires-Dist: nostalgic
